CHANGES.txt
README.txt
bootstrap.py
buildout.cfg
setup.py
flash/fla/debug.as
flash/fla/upload.fla
flash/src/z3c/widgets/flashupload/baseskin/ScrollBox.as
flash/src/z3c/widgets/flashupload/baseskin/Upload.as
src/z3c/__init__.py
src/z3c.widgets.flashupload.egg-info/PKG-INFO
src/z3c.widgets.flashupload.egg-info/SOURCES.txt
src/z3c.widgets.flashupload.egg-info/dependency_links.txt
src/z3c.widgets.flashupload.egg-info/namespace_packages.txt
src/z3c.widgets.flashupload.egg-info/not-zip-safe
src/z3c.widgets.flashupload.egg-info/requires.txt
src/z3c.widgets.flashupload.egg-info/top_level.txt
src/z3c/widgets/__init__.py
src/z3c/widgets/flashupload/README.txt
src/z3c/widgets/flashupload/__init__.py
src/z3c/widgets/flashupload/configure.zcml
src/z3c/widgets/flashupload/flashuploadvars.pt
src/z3c/widgets/flashupload/i18n.py
src/z3c/widgets/flashupload/interfaces.py
src/z3c/widgets/flashupload/noflashupload.pt
src/z3c/widgets/flashupload/tests.py
src/z3c/widgets/flashupload/ticket.py
src/z3c/widgets/flashupload/upload.py
src/z3c/widgets/flashupload/uploadform.pt
src/z3c/widgets/flashupload/locales/z3c.widget.flashupload.pot
src/z3c/widgets/flashupload/locales/de/LC_MESSAGES/z3c.widget.flashupload.mo
src/z3c/widgets/flashupload/locales/de/LC_MESSAGES/z3c.widget.flashupload.po
src/z3c/widgets/flashupload/locales/en/LC_MESSAGES/z3c.widget.flashupload.mo
src/z3c/widgets/flashupload/locales/en/LC_MESSAGES/z3c.widget.flashupload.po
src/z3c/widgets/flashupload/locales/fr/LC_MESSAGES/z3c.widget.flashupload.mo
src/z3c/widgets/flashupload/locales/fr/LC_MESSAGES/z3c.widget.flashupload.po
src/z3c/widgets/flashupload/locales/hu/LC_MESSAGES/z3c.widget.flashupload.mo
src/z3c/widgets/flashupload/locales/hu/LC_MESSAGES/z3c.widget.flashupload.po
src/z3c/widgets/flashupload/locales/ro/LC_MESSAGES/z3c.widget.flashupload.mo
src/z3c/widgets/flashupload/locales/ro/LC_MESSAGES/z3c.widget.flashupload.po
src/z3c/widgets/flashupload/resources/swfobject.js
src/z3c/widgets/flashupload/resources/upload.js
src/z3c/widgets/flashupload/resources/upload.swf