Metadata-Version: 1.0
Name: z3c.widgets.flashupload
Version: 1.0c1
Summary: Zope Flash Upload Widget
Home-page: http://pypi.python.org/pypi/z3c.widgets.flashupload
Author: Zope Community
Author-email: zope-dev@zope.org
License: ZPL 2.1
Keywords: zope
Platform: UNKNOWN
Classifier: Environment :: Web Environment
Classifier: Framework :: Zope3
Classifier: Intended Audience :: Developers
Classifier: License :: OSI Approved :: Zope Public License
Classifier: License :: OSI Approved :: GNU Library or Lesser General Public License (LGPL)
Classifier: Programming Language :: Python
